lib/__init__.py
lib/ok.py
cg3-6.6.6.dist-info/METADATA
cg3-6.6.6.dist-info/WHEEL
cg3-6.6.6.dist-info/top_level.txt
cg3-6.6.6.dist-info/RECORD
